Metadata-Version: 2.1
Name: bgno
Version: 0.1
Summary: Gaussian and Binomial distributions
Author-email: arturgugasian@gmail.com
